better_lbnl_os/__init__.py
better_lbnl_os/py.typed
better_lbnl_os/constants/__init__.py
better_lbnl_os/constants/building_types.py
better_lbnl_os/constants/energy.py
better_lbnl_os/constants/mappings.py
better_lbnl_os/constants/measures.py
better_lbnl_os/constants/recommendations.py
better_lbnl_os/constants/savings.py
better_lbnl_os/constants/template_parsing.py
better_lbnl_os/constants/thresholds.py
better_lbnl_os/core/__init__.py
better_lbnl_os/core/benchmarking.py
better_lbnl_os/core/changepoint.py
better_lbnl_os/core/defaults.py
better_lbnl_os/core/pipeline.py
better_lbnl_os/core/preprocessing.py
better_lbnl_os/core/recommendations.py
better_lbnl_os/core/savings.py
better_lbnl_os/core/services.py
better_lbnl_os/core/geocoding/interfaces.py
better_lbnl_os/core/geocoding/providers.py
better_lbnl_os/core/weather/__init__.py
better_lbnl_os/core/weather/calculations.py
better_lbnl_os/core/weather/interfaces.py
better_lbnl_os/core/weather/providers.py
better_lbnl_os/core/weather/service.py
better_lbnl_os/core/weather/providers/__init__.py
better_lbnl_os/core/weather/providers/noaa.py
better_lbnl_os/core/weather/providers/open_meteo.py
better_lbnl_os/data/__init__.py
better_lbnl_os/data/loader.py
better_lbnl_os/data/reference_data_models.py
better_lbnl_os/data/defaults/US_fuel_price_2024.csv
better_lbnl_os/data/defaults/egrid_emission_factors_2024.json
better_lbnl_os/data/defaults/fossil_emission_factors_2024.json
better_lbnl_os/data/defaults/manifest.json
better_lbnl_os/data/defaults/reference_statistics.json
better_lbnl_os/data/defaults/zip_region_map.csv
better_lbnl_os/data/schemas/reference_schema.json
better_lbnl_os/io/templates/__init__.py
better_lbnl_os/io/templates/better_excel.py
better_lbnl_os/io/templates/detect.py
better_lbnl_os/io/templates/portfolio_manager.py
better_lbnl_os/io/templates/types.py
better_lbnl_os/models/__init__.py
better_lbnl_os/models/benchmarking.py
better_lbnl_os/models/building.py
better_lbnl_os/models/location.py
better_lbnl_os-0.1.1.dist-info/METADATA
better_lbnl_os-0.1.1.dist-info/WHEEL
better_lbnl_os-0.1.1.dist-info/licenses/LICENSE
better_lbnl_os-0.1.1.dist-info/RECORD
