Metadata-Version: 2.4
Name: better-lbnl-os
Version: 0.1.1
Summary: Open-source building energy analytics library from BETTER (Building Efficiency Targeting Tool for Energy Retrofits)
Project-URL: Homepage, https://github.com/LBNL-ETA/better-lbnl-os
Project-URL: Documentation, https://better-lbnl-os.readthedocs.io
Project-URL: Repository, https://github.com/LBNL-ETA/better-lbnl-os
Project-URL: Issues, https://github.com/LBNL-ETA/better-lbnl-os/issues
Project-URL: Changelog, https://github.com/LBNL-ETA/better-lbnl-os/blob/main/CHANGELOG.md
Author-email: Han Li <hanli@lbl.gov>
Maintainer-email: Han Li <hanli@lbl.gov>
License: Building Efficiency Targeting Tool for Energy Retrofits (BETTER), Copyright (c) 2018, 
License-File: LICENSE
Keywords: BETTER,LBNL,benchmarking,building energy,change-point model,energy analytics,energy efficiency
Classifier: Development Status :: 3 - Alpha
Classifier: Intended Audience :: Developers
Classifier: Intended Audience :: Science/Research
Classifier: License :: OSI Approved :: BSD License
Classifier: Operating System :: OS Independent
Classifier: Programming Language :: Python
Classifier: Programming Language :: Python :: 3
Classifier: Programming Language :: Python :: 3.10
Classifier: Programming Language :: Python :: 3.11
Classifier: Programming Language :: Python :: 3.12
Classifier: Programming Language :: Python :: 3.13
Classifier: Topic :: Scientific/Engineering
Classifier: Topic :: Scientific/Engineering :: Information Analysis
Classifier: Topic :: Software Development :: Libraries :: Python Modules
Requires-Python: >=3.10
Requires-Dist: geocoder>=1.38.1
Requires-Dist: matplotlib>=3.5.0
Requires-Dist: numpy>=1.21.0
Requires-Dist: openpyxl>=3.1.0
Requires-Dist: pandas>=1.3.0
Requires-Dist: pydantic>=2.0.0
Requires-Dist: python-dateutil>=2.8.0
Requires-Dist: requests>=2.28.0
Requires-Dist: scipy>=1.7.0
Provides-Extra: all
Requires-Dist: black>=23.0.0; extra == 'all'
Requires-Dist: ipykernel>=6.0.0; extra == 'all'
Requires-Dist: ipywidgets>=8.0.0; extra == 'all'
Requires-Dist: isort>=5.12.0; extra == 'all'
Requires-Dist: jupyter>=1.0.0; extra == 'all'
Requires-Dist: matplotlib>=3.5.0; extra == 'all'
Requires-Dist: mypy>=1.0.0; extra == 'all'
Requires-Dist: nbsphinx>=0.9.0; extra == 'all'
Requires-Dist: notebook>=6.4.0; extra == 'all'
Requires-Dist: plotly>=5.0.0; extra == 'all'
Requires-Dist: pre-commit>=3.0.0; extra == 'all'
Requires-Dist: pytest-cov>=4.0.0; extra == 'all'
Requires-Dist: pytest-mock>=3.10.0; extra == 'all'
Requires-Dist: pytest>=7.0.0; extra == 'all'
Requires-Dist: ruff>=0.1.0; extra == 'all'
Requires-Dist: sphinx-autodoc-typehints>=1.23.0; extra == 'all'
Requires-Dist: sphinx-rtd-theme>=1.3.0; extra == 'all'
Requires-Dist: sphinx>=6.0.0; extra == 'all'
Requires-Dist: types-requests>=2.28.0; extra == 'all'
Provides-Extra: dev
Requires-Dist: black>=23.0.0; extra == 'dev'
Requires-Dist: ipykernel>=6.0.0; extra == 'dev'
Requires-Dist: isort>=5.12.0; extra == 'dev'
Requires-Dist: matplotlib>=3.5.0; extra == 'dev'
Requires-Dist: mypy>=1.0.0; extra == 'dev'
Requires-Dist: nbsphinx>=0.9.0; extra == 'dev'
Requires-Dist: pre-commit>=3.0.0; extra == 'dev'
Requires-Dist: pytest-cov>=4.0.0; extra == 'dev'
Requires-Dist: pytest-mock>=3.10.0; extra == 'dev'
Requires-Dist: pytest>=7.0.0; extra == 'dev'
Requires-Dist: ruff>=0.1.0; extra == 'dev'
Requires-Dist: sphinx-autodoc-typehints>=1.23.0; extra == 'dev'
Requires-Dist: sphinx-rtd-theme>=1.3.0; extra == 'dev'
Requires-Dist: sphinx>=6.0.0; extra == 'dev'
Requires-Dist: types-requests>=2.28.0; extra == 'dev'
Provides-Extra: examples
Requires-Dist: ipywidgets>=8.0.0; extra == 'examples'
Requires-Dist: jupyter>=1.0.0; extra == 'examples'
Requires-Dist: notebook>=6.4.0; extra == 'examples'
Provides-Extra: viz
Requires-Dist: matplotlib>=3.5.0; extra == 'viz'
Requires-Dist: plotly>=5.0.0; extra == 'viz'
